Workbook
Name aporte: simulador!$D$19
Name CENÁRIOS: simulador!$B$25:$D$30
Name CONFIGURAÇÕES: simulador!$B$13:$D$16
Name INVESTIMENTO_MENSAL: simulador!$B$18:$D$23
Name patrimonio: simulador!$D$22
Name PERFIL_DE_INVESTIDOR: simulador!$B$33:$D$44
Name qnt_anos: simulador!$D$20
Name rendimento_carteira: simulador!$D$15
Name salario: simulador!$D$14
Name sugestao_investimento: simulador!$D$16
Name taxa_mensal: simulador!$D$21

Sheet simulador
B13: CONFIGURAÇÕES
B14: Salário | D14: 10000
B15: Rendimento Carteira (%) | D15: 0.0098
B16: Sugestão de Investimento | D16: =D14*30% -> 3000
B18: INVESTIMENTO MENSAL
B19: Valor investido por mês | D19: 2000
B20: Tempo (anos) | D20: 10
B21: Taxa de rendimento mensal | D21: =rendimento_carteira -> 0.0098
B22: Patrimônio acumulado | D22: =FV(rendimento_carteira,qnt_anos*12,aporte*-1) -> 453648.72
B23: Dividendos mensais | D23: =patrimonio*rendimento_carteira -> 4445.7574
B25: CENÁRIOS | D25: DIVIDENDOS MENSAIS
B26: Patrimônio em 2 anos | C26: =FV($D$21,2*12,$D$19*-1) -> 53819.181 | D26: =C26*rendimento_carteira -> 527.42798
B27: Patrimônio em 5 anos | C27: =FV($D$21,5*12,$D$19*-1) -> 162293.43 | D27: =C27*rendimento_carteira -> 1590.4756
B28: Patrimônio em 10 anos | C28: =FV($D$21,10*12,$D$19*-1) -> 453648.72 | D28: =C28*rendimento_carteira -> 4445.7574
B29: Patrimônio em 20 anos | C29: =FV($D$21,20*12,$D$19*-1) -> 1915703.5 | D29: =C29*rendimento_carteira -> 18773.895
B30: Patrimônio em 30 anos | C30: =FV($D$21,30*12,$D$19*-1) -> 6627728.8 | D30: =C30*rendimento_carteira -> 64951.743
B33: PERFIL DE INVESTIDOR | C33: Conservador
B34: Valor a ser investido por mês | C34: =aporte -> 2000
B37: TIPO DE FII | C37: PERCENTUAL SUGERIDO | D37: VALORES
B38: Papel | C38: =VLOOKUP($C$33&"-"&B38,apoio!$A$3:$D$21,4,) -> 0.3 | D38: =$C$34*C38 -> 600
B39: Tijolo | C39: =VLOOKUP($C$33&"-"&B39,apoio!$A$3:$D$21,4,) -> 0.5 | D39: =$C$34*C39 -> 1000
B40: Híbridos | C40: =VLOOKUP($C$33&"-"&B40,apoio!$A$3:$D$21,4,) -> 0.1 | D40: =$C$34*C40 -> 200
B41: FOFs | C41: =VLOOKUP($C$33&"-"&B41,apoio!$A$3:$D$21,4,) -> 0.1 | D41: =$C$34*C41 -> 200
B42: Desenvolvimento | C42: =VLOOKUP($C$33&"-"&B42,apoio!$A$3:$D$21,4,) -> 0 | D42: =$C$34*C42 -> 0
B43: Hotelarias | C43: =VLOOKUP($C$33&"-"&B43,apoio!$A$3:$D$21,4,) -> 0 | D43: =$C$34*C43 -> 0
D44: =SUM(D38:D43) -> 2000

Sheet apoio
A3: CHAVE | B3: PERFIL | C3: TIPO DE FII | D3: PERCENTUAL
A4: Conservador-Papel | B4: Conservador | C4: Papel | D4: 0.3
A5: Conservador-Tijolo | B5: Conservador | C5: Tijolo | D5: 0.5
A6: Conservador-Híbridos | B6: Conservador | C6: Híbridos | D6: 0.1
A7: Conservador-FOFs | B7: Conservador | C7: FOFs | D7: 0.1
A8: Conservador-Desenvolvimento | B8: Conservador | C8: Desenvolvimento | D8: 0
A9: Conservador-Hotelarias | B9: Conservador | C9: Hotelarias | D9: 0
A10: Moderado-Papel | B10: Moderado | C10: Papel | D10: 0.32
A11: Moderado-Tijolo | B11: Moderado | C11: Tijolo | D11: 0.4
A12: Moderado-Híbridos | B12: Moderado | C12: Híbridos | D12: 0.08
A13: Moderado-FOFs | B13: Moderado | C13: FOFs | D13: 0.1
A14: Moderado-Desenvolvimento | B14: Moderado | C14: Desenvolvimento | D14: 0.05
A15: Moderado-Hotelarias | B15: Moderado | C15: Hotelarias | D15: 0.05
... A21: Agressivo-Hotelarias | B21: Agressivo | C21: Hotelarias | D21: 0.1
